{
	"Black Coffee": {
		"title": "Cà phê đen",
		"price": "30k",
		"image": "./images/black-coffee.webp",
		"alt": "Black Coffee",
		"info": "Một tách cà phê đen thơm ngào ngạt, phảng phất mùi cacao là món quà tự thưởng tuyệt vời nhất cho những ai mê đắm tinh chất nguyên bản nhất của cà phê. Một tách cà phê trầm lắng, thi vị giữa dòng đời vồn vã."
	},
	"Latte": {
		"title": "Latte",
		"price": "50k",
		"image": "./images/latte.webp",
		"alt": "Latte",
		"info": "Có nguồn gốc từ đất nước Ý xa xôi nhưng ngày nay, Latte đã trở thành loại café được ưa chuộng khắp thế giới, kể cả Việt Nam vì hương vị thơm ngon tuyệt hảo và cách pha chế mang khuynh hướng hiện đại."
	}
}
